rabbit_shell/__init__.py
rabbit_shell/__main__.py
rabbit_shell/auther/auther.py
rabbit_shell/background/backstuff.py
rabbit_shell/background/editor.py
rabbit_shell/background/generate.py
rabbit_shell/background/logger.py
rabbit_shell/background/record.py
rabbit_shell/background/teleport.py
rabbit_shell/client/client.py
rabbit_shell/controller/client_side.py
rabbit_shell/controller/server_side.py
rabbit_shell/data/about.py
rabbit_shell/data/basic.py
rabbit_shell/data/data.py
rabbit_shell/data/banners/banner.py
rabbit_shell/data/banners/rabbit.txt
rabbit_shell/server/server.py
rabbit_shell/server/test.txt
rabbit_shell/stream/screen.py
rabbit_shell/stream/shared.py
rabbit_shell/stream/webcam.py
rabbit_shell-3.3.3.dist-info/LICENSE
rabbit_shell-3.3.3.dist-info/METADATA
rabbit_shell-3.3.3.dist-info/WHEEL
rabbit_shell-3.3.3.dist-info/entry_points.txt
rabbit_shell-3.3.3.dist-info/top_level.txt
rabbit_shell-3.3.3.dist-info/RECORD
